{
  "name": "person",
  "schema": {
    "description": "This is an object representing a person associated with a Stripe account.\n\nA platform cannot access a Standard or Express account's persons after the account starts onboarding, such as after generating an account link for the account.\nSee the [Standard onboarding](https://stripe.com/docs/connect/standard-accounts) or [Express onboarding documentation](https://stripe.com/docs/connect/express-accounts) for information about platform pre-filling and account onboarding steps.\n\nRelated guide: [Handling Identity Verification with the API](https://stripe.com/docs/connect/identity-verification-api#person-information).",
    "properties": {
      "account": {
        "description": "The account the person is associated with.",
        "maxLength": 5000,
        "type": "string"
      },
      "address": {
        "city": "string",
        "country": "string",
        "line1": "string",
        "line2": "string",
        "postal_code": "string",
        "state": "string"
      },
      "address_kana": {
        "city": "string",
        "country": "string",
        "line1": "string",
        "line2": "string",
        "postal_code": "string",
        "state": "string",
        "town": "string"
      },
      "address_kanji": {
        "city": "string",
        "country": "string",
        "line1": "string",
        "line2": "string",
        "postal_code": "string",
        "state": "string",
        "town": "string"
      },
      "created": {
        "description": "Time at which the object was created. Measured in seconds since the Unix epoch.",
        "format": "unix-time",
        "type": "integer"
      },
      "dob": {
        "day": 0,
        "month": 0,
        "year": 0
      },
      "email": {
        "description": "The person's email address.",
        "maxLength": 5000,
        "nullable": true,
        "type": "string"
      },
      "first_name": {
        "description": "The person's first name.",
        "maxLength": 5000,
        "nullable": true,
        "type": "string"
      },
      "first_name_kana": {
        "description": "The Kana variation of the person's first name (Japan only).",
        "maxLength": 5000,
        "nullable": true,
        "type": "string"
      },
      "first_name_kanji": {
        "description": "The Kanji variation of the person's first name (Japan only).",
        "maxLength": 5000,
        "nullable": true,
        "type": "string"
      },
      "gender": {
        "description": "The person's gender (International regulations require either \"male\" or \"female\").",
        "maxLength": 5000,
        "nullable": true,
        "type": "string"
      },
      "id": {
        "description": "Unique identifier for the object.",
        "maxLength": 5000,
        "type": "string"
      },
      "id_number_provided": {
        "description": "Whether the person's `id_number` was provided.",
        "type": "boolean"
      },
      "last_name": {
        "description": "The person's last name.",
        "maxLength": 5000,
        "nullable": true,
        "type": "string"
      },
      "last_name_kana": {
        "description": "The Kana variation of the person's last name (Japan only).",
        "maxLength": 5000,
        "nullable": true,
        "type": "string"
      },
      "last_name_kanji": {
        "description": "The Kanji variation of the person's last name (Japan only).",
        "maxLength": 5000,
        "nullable": true,
        "type": "string"
      },
      "maiden_name": {
        "description": "The person's maiden name.",
        "maxLength": 5000,
        "nullable": true,
        "type": "string"
      },
      "metadata": {},
      "object": {
        "description": "String representing the object's type. Objects of the same type share the same value.",
        "enum": [
          "person"
        ],
        "type": "string"
      },
      "phone": {
        "description": "The person's phone number.",
        "maxLength": 5000,
        "nullable": true,
        "type": "string"
      },
      "political_exposure": {
        "description": "Indicates if the person or any of their representatives, family members, or other closely related persons, declares that they hold or have held an important public job or function, in any jurisdiction.",
        "enum": [
          "existing",
          "none"
        ],
        "type": "string"
      },
      "relationship": {
        "description": "",
        "properties": {
          "director": {
            "description": "Whether the person is a director of the account's legal entity. Currently only required for accounts in the EU. Directors are typically members of the governing board of the company, or responsible for ensuring the company meets its regulatory obligations.",
            "nullable": true,
            "type": "boolean"
          },
          "executive": {
            "description": "Whether the person has significant responsibility to control, manage, or direct the organization.",
            "nullable": true,
            "type": "boolean"
          },
          "owner": {
            "description": "Whether the person is an owner of the account’s legal entity.",
            "nullable": true,
            "type": "boolean"
          },
          "percent_ownership": {
            "description": "The percent owned by the person of the account's legal entity.",
            "nullable": true,
            "type": "number"
          },
          "representative": {
            "description": "Whether the person is authorized as the primary representative of the account. This is the person nominated by the business to provide information about themselves, and general information about the account. There can only be one representative at any given time. At the time the account is created, this person should be set to the person responsible for opening the account.",
            "nullable": true,
            "type": "boolean"
          },
          "title": {
            "description": "The person's title (e.g., CEO, Support Engineer).",
            "maxLength": 5000,
            "nullable": true,
            "type": "string"
          }
        },
        "title": "PersonRelationship",
        "type": "object",
        "x-expandableFields": []
      },
      "requirements": {
        "description": "",
        "properties": {
          "currently_due": {
            "maxLength": 5000,
            "type": "string"
          },
          "errors": {
            "code": "invalid_address_city_state_postal_code",
            "reason": "string",
            "requirement": "string"
          },
          "eventually_due": {
            "maxLength": 5000,
            "type": "string"
          },
          "past_due": {
            "maxLength": 5000,
            "type": "string"
          },
          "pending_verification": {
            "maxLength": 5000,
            "type": "string"
          }
        },
        "required": [
          "currently_due",
          "errors",
          "eventually_due",
          "past_due",
          "pending_verification"
        ],
        "title": "PersonRequirements",
        "type": "object",
        "x-expandableFields": [
          "errors"
        ]
      },
      "ssn_last_4_provided": {
        "description": "Whether the last four digits of the person's Social Security number have been provided (U.S. only).",
        "type": "boolean"
      },
      "verification": {
        "additional_document": {
          "back": "string",
          "details": "string",
          "details_code": "string",
          "front": "string"
        },
        "details": "string",
        "details_code": "string",
        "document": {
          "back": "string",
          "details": "string",
          "details_code": "string",
          "front": "string"
        },
        "status": "string"
      }
    },
    "required": [
      "account",
      "created",
      "id",
      "object"
    ],
    "title": "Person",
    "type": "object",
    "x-expandableFields": [
      "address",
      "address_kana",
      "address_kanji",
      "dob",
      "relationship",
      "requirements",
      "verification"
    ],
    "x-resourceId": "person",
    "default": {
      "account": "string",
      "address": {},
      "address_kana": {},
      "address_kanji": {},
      "created": 0,
      "dob": {},
      "email": "string",
      "first_name": "string",
      "first_name_kana": "string",
      "first_name_kanji": "string",
      "gender": "string",
      "id": "string",
      "id_number_provided": true,
      "last_name": "string",
      "last_name_kana": "string",
      "last_name_kanji": "string",
      "maiden_name": "string",
      "metadata": {},
      "object": "person",
      "phone": "string",
      "political_exposure": "existing",
      "relationship": {
        "director": true,
        "executive": true,
        "owner": true,
        "percent_ownership": 0,
        "representative": true,
        "title": "string"
      },
      "requirements": {
        "currently_due": "string",
        "errors": {},
        "eventually_due": "string",
        "past_due": "string",
        "pending_verification": "string"
      },
      "ssn_last_4_provided": true,
      "verification": {}
    }
  }
}