{
  "name": "billing_details",
  "schema": {
    "description": "",
    "properties": {
      "address": {
        "city": "string",
        "country": "string",
        "line1": "string",
        "line2": "string",
        "postal_code": "string",
        "state": "string"
      },
      "email": {
        "description": "Email address.",
        "maxLength": 5000,
        "nullable": true,
        "type": "string"
      },
      "name": {
        "description": "Full name.",
        "maxLength": 5000,
        "nullable": true,
        "type": "string"
      },
      "phone": {
        "description": "Billing phone number (including extension).",
        "maxLength": 5000,
        "nullable": true,
        "type": "string"
      }
    },
    "title": "billing_details",
    "type": "object",
    "x-expandableFields": [
      "address"
    ],
    "default": {
      "address": {},
      "email": "string",
      "name": "string",
      "phone": "string"
    }
  }
}